CHANGELOG.md
drfcommon/__init__.py
drfcommon/choices.py
drfcommon/exceptions.py
drfcommon/helper.py
drfcommon/log.py
drfcommon/pagination.py
drfcommon/readme.md
drfcommon/response.py
drfcommon/serializers.py
drfcommon/view_base.py
drfcommon-0.1.9.16.dist-info/LICENSE
drfcommon-0.1.9.16.dist-info/WHEEL
drfcommon-0.1.9.16.dist-info/METADATA
drfcommon-0.1.9.16.dist-info/RECORD
