Metadata-Version: 2.1
Name: drfcommon
Version: 0.1.9.16
Summary: a common tools for drf
Home-page: https://github.com/pydtools/drfcommon/
Author: tplinux
Author-email: 2363176358@qq.com
Requires-Python: >=3.8
Classifier: Programming Language :: Python :: 3
Classifier: Programming Language :: Python :: 3.8
Classifier: Programming Language :: Python :: 3.9
Classifier: Programming Language :: Python :: 3.10
Classifier: Programming Language :: Python :: 3.11
Requires-Dist: django (>=2.2)
Requires-Dist: djangorestframework (>=3.10)
Project-URL: Bug Tracker, https://github.com/pydtools/pytimetools/issues
Project-URL: Documentation, https://github.com/pydtools/drfcommon/wiki
Project-URL: Repository, https://github.com/pydtools/drfcommon/
Project-URL: github, https://github.com/pydtools/pytimetools/
